to_do_cli_app/__init__.py
to_do_cli_app/config.json
to_do_cli_app/main.py
to_do_cli_app/tasks/0_tasks.txt
to_do_cli_app-0.1.2.dist-info/LICENSE
to_do_cli_app-0.1.2.dist-info/METADATA
to_do_cli_app-0.1.2.dist-info/WHEEL
to_do_cli_app-0.1.2.dist-info/entry_points.txt
to_do_cli_app-0.1.2.dist-info/top_level.txt
to_do_cli_app-0.1.2.dist-info/RECORD
