Metadata-Version: 2.1
Name: to-do-cli-app
Version: 0.1.2
Summary: A little task manager inside the terminal
Home-page: https://github.com/luxiopppp/to-do-cli-app
Author: luxiopppp
Classifier: Programming Language :: Python :: 3
Classifier: License :: OSI Approved :: MIT License
Classifier: Operating System :: OS Independent
Requires-Python: >=3.9
License-File: LICENSE
Requires-Dist: prompt-toolkit ==3.0.36
Requires-Dist: questionary ==2.0.1
Requires-Dist: wcwidth ==0.2.13
